LICENSE.txt
README.rst
setup.cfg
setup.py
src/GeneVecTools/__init__.py
src/GeneVecTools/encoder.py
src/GeneVecTools/mapper.py
src/GeneVecTools/reader.py
src/GeneVecTools/simSearch.py
src/GeneVecTools.egg-info/PKG-INFO
src/GeneVecTools.egg-info/SOURCES.txt
src/GeneVecTools.egg-info/dependency_links.txt
src/GeneVecTools.egg-info/requires.txt
src/GeneVecTools.egg-info/top_level.txt
src/GeneVecTools/extras/__init__.py
src/GeneVecTools/library/__init__.py
src/GeneVecTools/library/database.py
tests/__init__.py
tests/example/__init__.py