Metadata-Version: 2.1
Name: GeneVecTools
Version: 1.38
Summary: UNKNOWN
Home-page: https://github.com/danielum16/SecondProject
Author: Daniel Um
Author-email: danielum.16@gmail.com
License: danielum16license
Keywords: example project
Platform: UNKNOWN
